pingram/__init__.py
pingram/pingram.py
pingram-0.3.4.dist-info/licenses/LICENSE
pingram-0.3.4.dist-info/METADATA
pingram-0.3.4.dist-info/WHEEL
pingram-0.3.4.dist-info/top_level.txt
pingram-0.3.4.dist-info/RECORD
