Metadata-Version: 2.4
Name: pingram
Version: 0.3.4
Summary: Minimal Telegram alerting framework for bots and scripts.
Author: zvizr
License: MIT License
Project-URL: Homepage, https://github.com/zvizr/pingram
Project-URL: Repository, https://github.com/zvizr/pingram
Project-URL: Issues, https://github.com/zvizr/pingram/issues
Keywords: telegram,bot,alert,notification,notifier,push,messaging,python,minimal,selfhosted,cli,automation,infra,monitoring
Classifier: Programming Language :: Python :: 3
Classifier: Programming Language :: Python :: 3 :: Only
Classifier: License :: OSI Approved :: MIT License
Classifier: Operating System :: OS Independent
Requires-Python: >=3.7
License-File: LICENSE
Requires-Dist: httpx
Provides-Extra: dev
Requires-Dist: pytest; extra == "dev"
Requires-Dist: ruff; extra == "dev"
Dynamic: license-file
